unravel/__init__.py
unravel/american_football/__init__.py
unravel/american_football/_example_helpers/__init__.py
unravel/american_football/_example_helpers/utils.py
unravel/american_football/dataset/__init__.py
unravel/american_football/dataset/dataset.py
unravel/american_football/dataset/objects.py
unravel/american_football/graphs/__init__.py
unravel/american_football/graphs/graph_converter.py
unravel/american_football/graphs/graph_settings.py
unravel/american_football/graphs/features/__init__.py
unravel/american_football/graphs/features/adjacency_matrix.py
unravel/american_football/graphs/features/edge_features.py
unravel/american_football/graphs/features/node_features.py
unravel/classifiers/__init__.py
unravel/classifiers/crystal_graph.py
unravel/classifiers/crystal_graph_pyg.py
unravel/soccer/__init__.py
unravel/soccer/dataset/__init__.py
unravel/soccer/dataset/kloppy_polars.py
unravel/soccer/dataset/objects.py
unravel/soccer/dataset/utils.py
unravel/soccer/graphs/__init__.py
unravel/soccer/graphs/graph_converter.py
unravel/soccer/graphs/graph_settings.py
unravel/soccer/graphs/exceptions/__init__.py
unravel/soccer/graphs/exceptions/exceptions.py
unravel/soccer/graphs/exceptions/warnings.py
unravel/soccer/graphs/features/__init__.py
unravel/soccer/graphs/features/adjacency_matrix.py
unravel/soccer/graphs/features/adjacency_matrix_pl.py
unravel/soccer/graphs/features/edge_features.py
unravel/soccer/graphs/features/edge_features_pl.py
unravel/soccer/graphs/features/node_features.py
unravel/soccer/graphs/features/node_features_pl.py
unravel/soccer/models/__init__.py
unravel/soccer/models/pressing_intensity.py
unravel/soccer/models/utils.py
unravel/soccer/models/formations/__init__.py
unravel/soccer/models/formations/detection.py
unravel/soccer/models/formations/efpi.py
unravel/utils/__init__.py
unravel/utils/utils.py
unravel/utils/display/__init__.py
unravel/utils/display/colors.py
unravel/utils/display/video.py
unravel/utils/exceptions/__init__.py
unravelsports-1.2.1.dist-info/licenses/LICENSE
unravelsports-1.2.1.dist-info/METADATA
unravelsports-1.2.1.dist-info/WHEEL
unravelsports-1.2.1.dist-info/top_level.txt
unravelsports-1.2.1.dist-info/RECORD
