Metadata-Version: 2.4
Name: unravelsports
Version: 1.2.1
Summary: A project to analyze sports event and tracking data
Home-page: https://github.com/unravelsports/unravelsports
Author: Joris Bekkers
Author-email: joris@unravelsports.com
Classifier: Programming Language :: Python :: 3.11
Classifier: Programming Language :: Python :: 3.12
Classifier: Programming Language :: Python :: 3.13
Classifier: License :: OSI Approved :: Mozilla Public License 2.0 (MPL 2.0)
Classifier: Operating System :: OS Independent
Requires-Python: >=3.11
License-File: LICENSE
Requires-Dist: kloppy>=3.18.0
Requires-Dist: polars[numpy]>=1.35.0
Requires-Dist: scipy>=1.0.0
Provides-Extra: test
Requires-Dist: pytest==8.2.2; extra == "test"
Requires-Dist: black[jupyter]==24.4.2; extra == "test"
Requires-Dist: matplotlib>=3.9; extra == "test"
Requires-Dist: mplsoccer>=1.4; extra == "test"
Requires-Dist: spektral==1.2.0; extra == "test"
Requires-Dist: keras==2.14.0; extra == "test"
Requires-Dist: tensorflow>=2.14.0; (platform_machine != "arm64" or platform_system != "Darwin") and extra == "test"
Requires-Dist: tensorflow-macos>=2.14.0; (platform_machine == "arm64" and platform_system == "Darwin") and extra == "test"
Requires-Dist: torch>=2.5.0; extra == "test"
Requires-Dist: torch-geometric>=2.6.0; extra == "test"
Requires-Dist: torchmetrics>=1.0.0; extra == "test"
Requires-Dist: pytorch-lightning>=2.0.0; extra == "test"
Provides-Extra: test-py311
Requires-Dist: pytest==8.2.2; extra == "test-py311"
Requires-Dist: black[jupyter]==24.4.2; extra == "test-py311"
Requires-Dist: matplotlib>=3.9; extra == "test-py311"
Requires-Dist: mplsoccer>=1.4; extra == "test-py311"
Requires-Dist: spektral==1.2.0; extra == "test-py311"
Requires-Dist: keras==2.14.0; extra == "test-py311"
Requires-Dist: tensorflow>=2.14.0; (platform_machine != "arm64" or platform_system != "Darwin") and extra == "test-py311"
Requires-Dist: tensorflow-macos>=2.14.0; (platform_machine == "arm64" and platform_system == "Darwin") and extra == "test-py311"
Requires-Dist: torch>=2.5.0; extra == "test-py311"
Requires-Dist: torch-geometric>=2.6.0; extra == "test-py311"
Requires-Dist: torchmetrics>=1.0.0; extra == "test-py311"
Requires-Dist: pytorch-lightning>=2.0.0; extra == "test-py311"
Provides-Extra: test-torch
Requires-Dist: pytest==8.2.2; extra == "test-torch"
Requires-Dist: black[jupyter]==24.4.2; extra == "test-torch"
Requires-Dist: matplotlib>=3.9; extra == "test-torch"
Requires-Dist: mplsoccer>=1.4; extra == "test-torch"
Requires-Dist: torch>=2.5.0; extra == "test-torch"
Requires-Dist: torch-geometric>=2.6.0; extra == "test-torch"
Requires-Dist: torchmetrics>=1.0.0; extra == "test-torch"
Requires-Dist: pytorch-lightning>=2.0.0; extra == "test-torch"
Dynamic: author
Dynamic: author-email
Dynamic: classifier
Dynamic: description
Dynamic: description-content-type
Dynamic: home-page
Dynamic: license-file
Dynamic: provides-extra
Dynamic: requires-dist
Dynamic: requires-python
Dynamic: summary
